{"nodes": [{"id": "conflux_bundle_readme_doc", "label": "OpenSpine Full OpenSpec Conflux Bundle README", "file_type": "document", "source_file": "openspine-full-openspec-conflux-bundle/README.md", "source_location": null, "source_url": null, "captured_at": null, "author": null, "contributor": null}], "edges": [{"source": "conflux_bundle_readme_doc", "target": "openspine_conventions_doc", "relation": "references", "confidence": "EXTRACTED", "confidence_score": 1.0, "source_file": "openspine-full-openspec-conflux-bundle/README.md", "source_location": null, "weight": 1.0}, {"source": "conflux_bundle_readme_doc", "target": "spec_authority_composition", "relation": "references", "confidence": "EXTRACTED", "confidence_score": 1.0, "source_file": "openspine-full-openspec-conflux-bundle/README.md", "source_location": null, "weight": 1.0}, {"source": "conflux_bundle_readme_doc", "target": "spec_core_runtime_schemas", "relation": "references", "confidence": "EXTRACTED", "confidence_score": 1.0, "source_file": "openspine-full-openspec-conflux-bundle/README.md", "source_location": null, "weight": 1.0}, {"source": "conflux_bundle_readme_doc", "target": "spec_gate_action_api", "relation": "references", "confidence": "EXTRACTED", "confidence_score": 1.0, "source_file": "openspine-full-openspec-conflux-bundle/README.md", "source_location": null, "weight": 1.0}, {"source": "conflux_bundle_readme_doc", "target": "spec_telegram_owner_control", "relation": "references", "confidence": "EXTRACTED", "confidence_score": 1.0, "source_file": "openspine-full-openspec-conflux-bundle/README.md", "source_location": null, "weight": 1.0}, {"source": "conflux_bundle_readme_doc", "target": "spec_email_preview", "relation": "references", "confidence": "EXTRACTED", "confidence_score": 1.0, "source_file": "openspine-full-openspec-conflux-bundle/README.md", "source_location": null, "weight": 1.0}, {"source": "conflux_bundle_readme_doc", "target": "spec_digest_approval", "relation": "references", "confidence": "EXTRACTED", "confidence_score": 1.0, "source_file": "openspine-full-openspec-conflux-bundle/README.md", "source_location": null, "weight": 1.0}, {"source": "conflux_bundle_readme_doc", "target": "spec_development_process", "relation": "references", "confidence": "EXTRACTED", "confidence_score": 1.0, "source_file": "openspine-full-openspec-conflux-bundle/README.md", "source_location": null, "weight": 1.0}], "hyperedges": []}